Workbook

Sheet CML Report
S3: Ver: 11.29.2021
B4: Construction Contract Modification Log
B6: General Information: | M6: Legend: | P6: Contract Time Information:
B8: Project Number: | E8: AC-017630 | M8: White cells, project administrator will provide project information (input cells). | P8: Contract Beginning Date: | T8: 44348
B9: Federal Number: | E9: ZP-176(3) | P9: Original Contract Time: | T9: 420
B10: Oracle Number: | E10: F000176030 | M10: Color cells, the excel file will make calculations (formula cells). | P10: Original Termination Date: | T10: =IF(T8>0,(T8+T9-1)," ")
B11: Project Tittle: | E11: Highway Safety Improvements Highway PR-176, km 0.00 to 4.00 San Juan, PR | P11: Total Time Extensions (Days): | T11: =N223
B12: Contractor : | E12: Puerto Rico Asphalt, LLC | M12: Gray cells & Blue Font Color, attention is required (see comment in the cells). | P12: Revised Termination Date: | T12: =IF(T11>0,(T10+T11),T10)
B13: Project Manager: | E13: Ing. Luis R. Pastor Reyes | P13: Change in Contract Time (%): | T13: =IF(T8>0,((T11)/T9),0)
B14: Date: | E14: 45428 | M14: Red Cells, possible action by PRHTA (red flag). | P14: Time Completed to Date (%): | T14: =IF(I16="YES",IF(W14>1,1,W14),W14) | W14: =IF(E14>0,((E14-T8)/(T12-T8)),0)
M15: Red Font Color are for negative numbers or quantities. | P15: Change in Contract Amount (%): | T15: =IF(E225>0,(E225/E62),0)
B16: Has the project reached substantial completion? | H16: Y/N? | I16: NO | P16: % Work Performed to Date: | T16: 0.4
B17: No. of CHO documents: | E17: 4 | P17: Estimated Completion Date: | T17: 44767
B18: No. of EWO documents: | E18: 6 | P18: Administrative Date of Comptroller Office (Contralor): | T18: 45542 | W18: =T18-E14
P19: Project End Date (FMIS): | T19: 45145 | W19: =T19-E14
B22: Project Description: | E22: This project is located on Highway PR-176 from kilometer 0.00 to 4.00 for total length of 4 km. The Pavement Rehabiltation and Safety Improvement Project for PR-176, commences at its intersection with PR-1 and continue along the exixting highway up to the intersection with PR-199 in the municipality of San Juan. The proposed works consist of the improvements to the exixting roadside safety elements at highway PR-176. The works to be performed also include: maintenance and protection of traffic, cold milling and placement of bituminous pavement, the aplication thermoplastic pavement marking, installation of traffic signs, removal, storage and delivered of exixting guard rail, furnishing and installation of Wbeam guard rail single face and double face, contruction of new transition modules traffic signals and other miscellaneous works as shown on plans.
K27: NOTES:
B28: Is this project eligible for toll credits? | H28: Y/N? | I28: YES | K28: 1- Examples of projects that are not eligible for toll credits (answer to the question is NO): ER Projects and Old Projects without Toll Credits.
B29: Does the project have pay items with ER funds? | H29: Y/N? | I29: NO | K29: =IF(I29="NO","",IF(I29="","","2- Reminder: The project manager will develop separate ROAs for CHO or EWO with ER funded pay items from regular federally funded modifications."))
B31: Original Project Funds Information
B32: Units | C32: Federal Share % | E32: INPUT PROJECT AGREEMENT | K32: FEDERAL FUNDS | O32: STATE FUNDS
E33: Participating | G33: Contingencies (Participating) | I33: Payroll, Mileage and Diets | K33: F.A. Funds Requested | L33: Contingencies (Federal Funds) | M33: Calculation of Toll Credits | N33: Contingencies (Toll Credits) | O33: State Share of Federal Funds | P33: Contingencies (State Share) | Q33: Not Participating (State Funds) | R33: Contingencies (Not Participating) | T33: Payroll, Mileage and Diets
B35: Unit 1 | C35: =IF(K35>0,(K35)/(E35+G35+I35),"N/A") | E35: 1937696 | G35: 193769.6 | K35: 1710501.1 | L35: =ROUND(IF(C35="N/A",0,G35*C35),2) | M35: =ROUND(IF($I$28="YES",IF(C35="N/A",0,(E35+G35+I35)*(1-C35)),0),2) | N35: =ROUND(IF($I$28="YES",IF(C35="N/A",0,G35*(1-C35)),0),2) | O35: =ROUND(IF($I$28="NO",IF(C35="N/A",0,(E35+G35+I35)*(1-C35)),0),2) | P35: =ROUND(IF($I$28="NO",IF(C35="N/A",0,G35*(1-C35)),0),2) | Q35: 58670 | R35: 5867
B36: Unit 2 | C36: =IF(K36>0,(K36)/(E36+G36+I36),"N/A") | E36: 44161 | G36: 4416.1 | K36: 48577.1 | L36: =ROUND(IF(C36="N/A",0,G36*C36),2) | M36: =ROUND(IF($I$28="YES",IF(C36="N/A",0,(E36+G36+I36)*(1-C36)),0),2) | N36: =ROUND(IF($I$28="YES",IF(C36="N/A",0,G36*(1-C36)),0),2) | O36: =ROUND(IF($I$28="NO",IF(C36="N/A",0,(E36+G36+I36)*(1-C36)),0),2) | P36: =ROUND(IF($I$28="NO",IF(C36="N/A",0,G36*(1-C36)),0),2) | Q36: 0 | R36: 0
B37: Unit 3 | C37: =IF(K37>0,(K37)/(E37+G37+I37),"N/A") | E37: 218354 | G37: 21835.4 | K37: 240189.4 | L37: =ROUND(IF(C37="N/A",0,G37*C37),2) | M37: =ROUND(IF($I$28="YES",IF(C37="N/A",0,(E37+G37+I37)*(1-C37)),0),2) | N37: =ROUND(IF($I$28="YES",IF(C37="N/A",0,G37*(1-C37)),0),2) | O37: =ROUND(IF($I$28="NO",IF(C37="N/A",0,(E37+G37+I37)*(1-C37)),0),2) | P37: =ROUND(IF($I$28="NO",IF(C37="N/A",0,G37*(1-C37)),0),2) | Q37: 0 | R37: 0
B38: Unit 4 | C38: =IF(K38>0,(K38)/(E38+G38+I38),"N/A") | E38: 858618 | G38: 85861.8 | K38: 757945.03 | L38: =ROUND(IF(C38="N/A",0,G38*C38),2) | M38: =ROUND(IF($I$28="YES",IF(C38="N/A",0,(E38+G38+I38)*(1-C38)),0),2) | N38: =ROUND(IF($I$28="YES",IF(C38="N/A",0,G38*(1-C38)),0),2) | O38: =ROUND(IF($I$28="NO",IF(C38="N/A",0,(E38+G38+I38)*(1-C38)),0),2) | P38: =ROUND(IF($I$28="NO",IF(C38="N/A",0,G38*(1-C38)),0),2) | Q38: 20000 | R38: 2000
B39: Unit 5 | C39: =IF(K39>0,(K39)/(E39+G39+I39),"N/A") | L39: =ROUND(IF(C39="N/A",0,G39*C39),2) | M39: =ROUND(IF($I$28="YES",IF(C39="N/A",0,(E39+G39+I39)*(1-C39)),0),2) | N39: =ROUND(IF($I$28="YES",IF(C39="N/A",0,G39*(1-C39)),0),2) | O39: =ROUND(IF($I$28="NO",IF(C39="N/A",0,(E39+G39+I39)*(1-C39)),0),2) | P39: =ROUND(IF($I$28="NO",IF(C39="N/A",0,G39*(1-C39)),0),2)
B40: Unit 6 | C40: =IF(K40>0,(K40)/(E40+G40+I40),"N/A") | L40: =ROUND(IF(C40="N/A",0,G40*C40),2) | M40: =ROUND(IF($I$28="YES",IF(C40="N/A",0,(E40+G40+I40)*(1-C40)),0),2) | N40: =ROUND(IF($I$28="YES",IF(C40="N/A",0,G40*(1-C40)),0),2) | O40: =ROUND(IF($I$28="NO",IF(C40="N/A",0,(E40+G40+I40)*(1-C40)),0),2) | P40: =ROUND(IF($I$28="NO",IF(C40="N/A",0,G40*(1-C40)),0),2)
B41: Unit 7 | C41: =IF(K41>0,(K41)/(E41+G41+I41),"N/A") | L41: =ROUND(IF(C41="N/A",0,G41*C41),2) | M41: =ROUND(IF($I$28="YES",IF(C41="N/A",0,(E41+G41+I41)*(1-C41)),0),2) | N41: =ROUND(IF($I$28="YES",IF(C41="N/A",0,G41*(1-C41)),0),2) | O41: =ROUND(IF($I$28="NO",IF(C41="N/A",0,(E41+G41+I41)*(1-C41)),0),2) | P41: =ROUND(IF($I$28="NO",IF(C41="N/A",0,G41*(1-C41)),0),2)
B42: Unit 8 | C42: =IF(K42>0,(K42)/(E42+G42+I42),"N/A") | L42: =ROUND(IF(C42="N/A",0,G42*C42),2) | M42: =ROUND(IF($I$28="YES",IF(C42="N/A",0,(E42+G42+I42)*(1-C42)),0),2) | N42: =ROUND(IF($I$28="YES",IF(C42="N/A",0,G42*(1-C42)),0),2) | O42: =ROUND(IF($I$28="NO",IF(C42="N/A",0,(E42+G42+I42)*(1-C42)),0),2) | P42: =ROUND(IF($I$28="NO",IF(C42="N/A",0,G42*(1-C42)),0),2)
B43: Unit 9 | C43: =IF(K43>0,(K43)/(E43+G43+I43),"N/A") | L43: =ROUND(IF(C43="N/A",0,G43*C43),2) | M43: =ROUND(IF($I$28="YES",IF(C43="N/A",0,(E43+G43+I43)*(1-C43)),0),2) | N43: =ROUND(IF($I$28="YES",IF(C43="N/A",0,G43*(1-C43)),0),2) | O43: =ROUND(IF($I$28="NO",IF(C43="N/A",0,(E43+G43+I43)*(1-C43)),0),2) | P43: =ROUND(IF($I$28="NO",IF(C43="N/A",0,G43*(1-C43)),0),2)
B44: Unit 10 | C44: =IF(K44>0,(K44)/(E44+G44+I44),"N/A") | L44: =ROUND(IF(C44="N/A",0,G44*C44),2) | M44: =ROUND(IF($I$28="YES",IF(C44="N/A",0,(E44+G44+I44)*(1-C44)),0),2) | N44: =ROUND(IF($I$28="YES",IF(C44="N/A",0,G44*(1-C44)),0),2) | O44: =ROUND(IF($I$28="NO",IF(C44="N/A",0,(E44+G44+I44)*(1-C44)),0),2) | P44: =ROUND(IF($I$28="NO",IF(C44="N/A",0,G44*(1-C44)),0),2)
B45: Unit 11 | C45: =IF(K45>0,(K45)/(E45+G45+I45),"N/A") | L45: =ROUND(IF(C45="N/A",0,G45*C45),2) | M45: =ROUND(IF($I$28="YES",IF(C45="N/A",0,(E45+G45+I45)*(1-C45)),0),2) | N45: =ROUND(IF($I$28="YES",IF(C45="N/A",0,G45*(1-C45)),0),2) | O45: =ROUND(IF($I$28="NO",IF(C45="N/A",0,(E45+G45+I45)*(1-C45)),0),2) | P45: =ROUND(IF($I$28="NO",IF(C45="N/A",0,G45*(1-C45)),0),2)
B46: Unit 12 | C46: =IF(K46>0,(K46)/(E46+G46+I46),"N/A") | L46: =ROUND(IF(C46="N/A",0,G46*C46),2) | M46: =ROUND(IF($I$28="YES",IF(C46="N/A",0,(E46+G46+I46)*(1-C46)),0),2) | N46: =ROUND(IF($I$28="YES",IF(C46="N/A",0,G46*(1-C46)),0),2) | O46: =ROUND(IF($I$28="NO",IF(C46="N/A",0,(E46+G46+I46)*(1-C46)),0),2) | P46: =ROUND(IF($I$28="NO",IF(C46="N/A",0,G46*(1-C46)),0),2)
B47: Unit 13 | C47: =IF(K47>0,(K47)/(E47+G47+I47),"N/A") | L47: =ROUND(IF(C47="N/A",0,G47*C47),2) | M47: =ROUND(IF($I$28="YES",IF(C47="N/A",0,(E47+G47+I47)*(1-C47)),0),2) | N47: =ROUND(IF($I$28="YES",IF(C47="N/A",0,G47*(1-C47)),0),2) | O47: =ROUND(IF($I$28="NO",IF(C47="N/A",0,(E47+G47+I47)*(1-C47)),0),2) | P47: =ROUND(IF($I$28="NO",IF(C47="N/A",0,G47*(1-C47)),0),2)
B48: Unit 14 | C48: =IF(K48>0,(K48)/(E48+G48+I48),"N/A") | L48: =ROUND(IF(C48="N/A",0,G48*C48),2) | M48: =ROUND(IF($I$28="YES",IF(C48="N/A",0,(E48+G48+I48)*(1-C48)),0),2) | N48: =ROUND(IF($I$28="YES",IF(C48="N/A",0,G48*(1-C48)),0),2) | O48: =ROUND(IF($I$28="NO",IF(C48="N/A",0,(E48+G48+I48)*(1-C48)),0),2) | P48: =ROUND(IF($I$28="NO",IF(C48="N/A",0,G48*(1-C48)),0),2)
B49: Unit 15 | C49: =IF(K49>0,(K49)/(E49+G49+I49),"N/A") | L49: =ROUND(IF(C49="N/A",0,G49*C49),2) | M49: =ROUND(IF($I$28="YES",IF(C49="N/A",0,(E49+G49+I49)*(1-C49)),0),2) | N49: =ROUND(IF($I$28="YES",IF(C49="N/A",0,G49*(1-C49)),0),2) | O49: =ROUND(IF($I$28="NO",IF(C49="N/A",0,(E49+G49+I49)*(1-C49)),0),2) | P49: =ROUND(IF($I$28="NO",IF(C49="N/A",0,G49*(1-C49)),0),2)
B50: Unit 16 | C50: =IF(K50>0,(K50)/(E50+G50+I50),"N/A") | L50: =ROUND(IF(C50="N/A",0,G50*C50),2) | M50: =ROUND(IF($I$28="YES",IF(C50="N/A",0,(E50+G50+I50)*(1-C50)),0),2) | N50: =ROUND(IF($I$28="YES",IF(C50="N/A",0,G50*(1-C50)),0),2) | O50: =ROUND(IF($I$28="NO",IF(C50="N/A",0,(E50+G50+I50)*(1-C50)),0),2) | P50: =ROUND(IF($I$28="NO",IF(C50="N/A",0,G50*(1-C50)),0),2)
... B59: Unit 25 | C59: =IF(K59>0,(K59)/(E59+G59+I59),"N/A") | L59: =ROUND(IF(C59="N/A",0,G59*C59),2) | M59: =ROUND(IF($I$28="YES",IF(C59="N/A",0,(E59+G59+I59)*(1-C59)),0),2) | N59: =ROUND(IF($I$28="YES",IF(C59="N/A",0,G59*(1-C59)),0),2) | O59: =ROUND(IF($I$28="NO",IF(C59="N/A",0,(E59+G59+I59)*(1-C59)),0),2) | P59: =ROUND(IF($I$28="NO",IF(C59="N/A",0,G59*(1-C59)),0),2)
B60: Sub Totals | E60: =SUM(E35:F59) | G60: =SUM(G35:H59) | I60: =SUM(I35:J59) | K60: =SUM(K35:K59) | L60: =SUM(L35:L59) | M60: =SUM(M35:M59) | N60: =SUM(N35:N59) | O60: =SUM(O35:O59) | P60: =SUM(P35:P59) | Q60: =SUM(Q35:Q59) | R60: =SUM(R35:S59) | T60: =SUM(T35:U59)
B61: Totals | K61: =K60+M60 | O61: =Q60+R60+T60+O60
B62: Eng. Contract Estimate: | E62: =E60+Q60 | H62: This is the original cost of the project (bid process).
B63: Total Construction Cost: | E63: =K61+O61 | H63: This is the total budget for the project. Includes federal and state funds, contingencies, and payroll or expenses when applicable.
B64: NOTE:
B65: 1- IF THE FEDERAL SHARE % COLUMN HAS VALUES DIFFERENT THAN 80.25%, 90% AND 100%, VERIFY THE INFORMATION INCLUDED IN THE TABLE BEFORE CONTINUING WITH THE PROCESS.
B67: Project Modification Documents
B68: Document # | D68: Proposed Amount | G68: Federal Share (%) | H68: Federal Share Amount | K68: Toll Credits Amount | L68: Non Participating Amount (State Funds) | M68: State Share of Federal Funds | N68: Time Extension (Days) | O68: Federal Share for Project Modification Letter | P68: Toll Credits for Project Modification Letter | Q68: Comments
B69: CHO | C69: EWO | W69: Fed Share | X69: Cumm Invertido | Y69: Add Funds - Cumm | Z69: Determine Funds | AB69: Toll Credits | AC69: Cumm Invertido | AD69: Add Funds - Cumm | AE69: Determine Funds
C70: 1 | D70: 6000 | G70: 0 | H70: =ROUND(G70*D70,2) | K70: =ROUND(IF($I$28="YES",IF(G70>0,D70*(1-G70),0),0),2) | L70: =ROUND(IF(G70=0,D70,0),2) | M70: =ROUND(IF($I$28="NO",IF(G70>0,D70*(1-G70),0),0),2) | O70: =ROUND(IF(Z70<0,0,Z70),2) | P70: =ROUND(IF($I$28="YES",IF(AE70<0,0,AE70),0),2) | W70: =H70 | X70: =IF(W70<0,X71,X71+W70) | Y70: =$W$226-X70 | Z70: =IF(Y70<0,Y71,H70) | AB70: =K70 | AC70: =IF(AB70<0,AC71,AC71+AB70) | AD70: =$X$226-AC70 | AE70: =IF(AD70<0,AD71,K70)
B71: 1 | D71: -73400 | G71: 0.8025 | H71: =ROUND(G71*D71,2) | K71: =ROUND(IF($I$28="YES",IF(G71>0,D71*(1-G71),0),0),2) | L71: =ROUND(IF(G71=0,D71,0),2) | M71: =ROUND(IF($I$28="NO",IF(G71>0,D71*(1-G71),0),0),2) | O71: =ROUND(IF(Z71<0,0,Z71),2) | P71: =ROUND(IF($I$28="YES",IF(AE71<0,0,AE71),0),2) | W71: =H71 | X71: =IF(W71<0,X72,X72+W71) | Y71: =$W$226-X71 | Z71: =IF(Y71<0,Y72,H71) | AB71: =K71 | AC71: =IF(AB71<0,AC72,AC72+AB71) | AD71: =$X$226-AC71 | AE71: =IF(AD71<0,AD72,K71)
B72: 1 | D72: 108000 | G72: 0.8025 | H72: =ROUND(G72*D72,2) | K72: =ROUND(IF($I$28="YES",IF(G72>0,D72*(1-G72),0),0),2) | L72: =ROUND(IF(G72=0,D72,0),2) | M72: =ROUND(IF($I$28="NO",IF(G72>0,D72*(1-G72),0),0),2) | O72: =ROUND(IF(Z72<0,0,Z72),2) | P72: =ROUND(IF($I$28="YES",IF(AE72<0,0,AE72),0),2) | W72: =H72 | X72: =IF(W72<0,X73,X73+W72) | Y72: =$W$226-X72 | Z72: =IF(Y72<0,Y73,H72) | AB72: =K72 | AC72: =IF(AB72<0,AC73,AC73+AB72) | AD72: =$X$226-AC72 | AE72: =IF(AD72<0,AD73,K72)
C73: 2 | D73: 450000 | G73: 0 | H73: =ROUND(G73*D73,2) | K73: =ROUND(IF($I$28="YES",IF(G73>0,D73*(1-G73),0),0),2) | L73: =ROUND(IF(G73=0,D73,0),2) | M73: =ROUND(IF($I$28="NO",IF(G73>0,D73*(1-G73),0),0),2) | O73: =ROUND(IF(Z73<0,0,Z73),2) | P73: =ROUND(IF($I$28="YES",IF(AE73<0,0,AE73),0),2) | W73: =H73 | X73: =IF(W73<0,X74,X74+W73) | Y73: =$W$226-X73 | Z73: =IF(Y73<0,Y74,H73) | AB73: =K73 | AC73: =IF(AB73<0,AC74,AC74+AB73) | AD73: =$X$226-AC73 | AE73: =IF(AD73<0,AD74,K73)
C74: 3 | D74: 24044 | G74: 0.8025 | H74: =ROUND(G74*D74,2) | K74: =ROUND(IF($I$28="YES",IF(G74>0,D74*(1-G74),0),0),2) | L74: =ROUND(IF(G74=0,D74,0),2) | M74: =ROUND(IF($I$28="NO",IF(G74>0,D74*(1-G74),0),0),2) | N74: 25 | O74: =ROUND(IF(Z74<0,0,Z74),2) | P74: =ROUND(IF($I$28="YES",IF(AE74<0,0,AE74),0),2) | W74: =H74 | X74: =IF(W74<0,X75,X75+W74) | Y74: =$W$226-X74 | Z74: =IF(Y74<0,Y75,H74) | AB74: =K74 | AC74: =IF(AB74<0,AC75,AC75+AB74) | AD74: =$X$226-AC74 | AE74: =IF(AD74<0,AD75,K74)
C75: 3 | D75: 9248 | G75: 0 | H75: =ROUND(G75*D75,2) | K75: =ROUND(IF($I$28="YES",IF(G75>0,D75*(1-G75),0),0),2) | L75: =ROUND(IF(G75=0,D75,0),2) | M75: =ROUND(IF($I$28="NO",IF(G75>0,D75*(1-G75),0),0),2) | O75: =ROUND(IF(Z75<0,0,Z75),2) | P75: =ROUND(IF($I$28="YES",IF(AE75<0,0,AE75),0),2) | W75: =H75 | X75: =IF(W75<0,X76,X76+W75) | Y75: =$W$226-X75 | Z75: =IF(Y75<0,Y76,H75) | AB75: =K75 | AC75: =IF(AB75<0,AC76,AC76+AB75) | AD75: =$X$226-AC75 | AE75: =IF(AD75<0,AD76,K75)
B76: 2 | D76: 366510 | G76: 0.8025 | H76: =ROUND(G76*D76,2) | K76: =ROUND(IF($I$28="YES",IF(G76>0,D76*(1-G76),0),0),2) | L76: =ROUND(IF(G76=0,D76,0),2) | M76: =ROUND(IF($I$28="NO",IF(G76>0,D76*(1-G76),0),0),2) | N76: 20 | O76: =ROUND(IF(Z76<0,0,Z76),2) | P76: =ROUND(IF($I$28="YES",IF(AE76<0,0,AE76),0),2) | W76: =H76 | X76: =IF(W76<0,X77,X77+W76) | Y76: =$W$226-X76 | Z76: =IF(Y76<0,Y77,H76) | AB76: =K76 | AC76: =IF(AB76<0,AC77,AC77+AB76) | AD76: =$X$226-AC76 | AE76: =IF(AD76<0,AD77,K76)
B77: 3 | D77: 48200 | H77: =ROUND(G77*D77,2) | K77: =ROUND(IF($I$28="YES",IF(G77>0,D77*(1-G77),0),0),2) | L77: =ROUND(IF(G77=0,D77,0),2) | M77: =ROUND(IF($I$28="NO",IF(G77>0,D77*(1-G77),0),0),2) | N77: 154 | O77: =ROUND(IF(Z77<0,0,Z77),2) | P77: =ROUND(IF($I$28="YES",IF(AE77<0,0,AE77),0),2) | W77: =H77 | X77: =IF(W77<0,X78,X78+W77) | Y77: =$W$226-X77 | Z77: =IF(Y77<0,Y78,H77) | AB77: =K77 | AC77: =IF(AB77<0,AC78,AC78+AB77) | AD77: =$X$226-AC77 | AE77: =IF(AD77<0,AD78,K77)
C78: 4 | D78: 1479970 | H78: =ROUND(G78*D78,2) | K78: =ROUND(IF($I$28="YES",IF(G78>0,D78*(1-G78),0),0),2) | L78: =ROUND(IF(G78=0,D78,0),2) | M78: =ROUND(IF($I$28="NO",IF(G78>0,D78*(1-G78),0),0),2) | O78: =ROUND(IF(Z78<0,0,Z78),2) | P78: =ROUND(IF($I$28="YES",IF(AE78<0,0,AE78),0),2) | W78: =H78 | X78: =IF(W78<0,X79,X79+W78) | Y78: =$W$226-X78 | Z78: =IF(Y78<0,Y79,H78) | AB78: =K78 | AC78: =IF(AB78<0,AC79,AC79+AB78) | AD78: =$X$226-AC78 | AE78: =IF(AD78<0,AD79,K78)
C79: 5 | D79: 48473 | H79: =ROUND(G79*D79,2) | K79: =ROUND(IF($I$28="YES",IF(G79>0,D79*(1-G79),0),0),2) | L79: =ROUND(IF(G79=0,D79,0),2) | M79: =ROUND(IF($I$28="NO",IF(G79>0,D79*(1-G79),0),0),2) | O79: =ROUND(IF(Z79<0,0,Z79),2) | P79: =ROUND(IF($I$28="YES",IF(AE79<0,0,AE79),0),2) | W79: =H79 | X79: =IF(W79<0,X80,X80+W79) | Y79: =$W$226-X79 | Z79: =IF(Y79<0,Y80,H79) | AB79: =K79 | AC79: =IF(AB79<0,AC80,AC80+AB79) | AD79: =$X$226-AC79 | AE79: =IF(AD79<0,AD80,K79)
C80: 6 | D80: 618332 | H80: =ROUND(G80*D80,2) | K80: =ROUND(IF($I$28="YES",IF(G80>0,D80*(1-G80),0),0),2) | L80: =ROUND(IF(G80=0,D80,0),2) | M80: =ROUND(IF($I$28="NO",IF(G80>0,D80*(1-G80),0),0),2) | O80: =ROUND(IF(Z80<0,0,Z80),2) | P80: =ROUND(IF($I$28="YES",IF(AE80<0,0,AE80),0),2) | W80: =H80 | X80: =IF(W80<0,X81,X81+W80) | Y80: =$W$226-X80 | Z80: =IF(Y80<0,Y81,H80) | AB80: =K80 | AC80: =IF(AB80<0,AC81,AC81+AB80) | AD80: =$X$226-AC80 | AE80: =IF(AD80<0,AD81,K80)
B81: 4 | D81: 185100 | H81: =ROUND(G81*D81,2) | K81: =ROUND(IF($I$28="YES",IF(G81>0,D81*(1-G81),0),0),2) | L81: =ROUND(IF(G81=0,D81,0),2) | M81: =ROUND(IF($I$28="NO",IF(G81>0,D81*(1-G81),0),0),2) | O81: =ROUND(IF(Z81<0,0,Z81),2) | P81: =ROUND(IF($I$28="YES",IF(AE81<0,0,AE81),0),2) | W81: =H81 | X81: =IF(W81<0,X82,X82+W81) | Y81: =$W$226-X81 | Z81: =IF(Y81<0,Y82,H81) | AB81: =K81 | AC81: =IF(AB81<0,AC82,AC82+AB81) | AD81: =$X$226-AC81 | AE81: =IF(AD81<0,AD82,K81)
H82: =ROUND(G82*D82,2) | K82: =ROUND(IF($I$28="YES",IF(G82>0,D82*(1-G82),0),0),2) | L82: =ROUND(IF(G82=0,D82,0),2) | M82: =ROUND(IF($I$28="NO",IF(G82>0,D82*(1-G82),0),0),2) | O82: =ROUND(IF(Z82<0,0,Z82),2) | P82: =ROUND(IF($I$28="YES",IF(AE82<0,0,AE82),0),2) | W82: =H82 | X82: =IF(W82<0,X83,X83+W82) | Y82: =$W$226-X82 | Z82: =IF(Y82<0,Y83,H82) | AB82: =K82 | AC82: =IF(AB82<0,AC83,AC83+AB82) | AD82: =$X$226-AC82 | AE82: =IF(AD82<0,AD83,K82)
H83: =ROUND(G83*D83,2) | K83: =ROUND(IF($I$28="YES",IF(G83>0,D83*(1-G83),0),0),2) | L83: =ROUND(IF(G83=0,D83,0),2) | M83: =ROUND(IF($I$28="NO",IF(G83>0,D83*(1-G83),0),0),2) | O83: =ROUND(IF(Z83<0,0,Z83),2) | P83: =ROUND(IF($I$28="YES",IF(AE83<0,0,AE83),0),2) | W83: =H83 | X83: =IF(W83<0,X84,X84+W83) | Y83: =$W$226-X83 | Z83: =IF(Y83<0,Y84,H83) | AB83: =K83 | AC83: =IF(AB83<0,AC84,AC84+AB83) | AD83: =$X$226-AC83 | AE83: =IF(AD83<0,AD84,K83)
H84: =ROUND(G84*D84,2) | K84: =ROUND(IF($I$28="YES",IF(G84>0,D84*(1-G84),0),0),2) | L84: =ROUND(IF(G84=0,D84,0),2) | M84: =ROUND(IF($I$28="NO",IF(G84>0,D84*(1-G84),0),0),2) | O84: =ROUND(IF(Z84<0,0,Z84),2) | P84: =ROUND(IF($I$28="YES",IF(AE84<0,0,AE84),0),2) | W84: =H84 | X84: =IF(W84<0,X85,X85+W84) | Y84: =$W$226-X84 | Z84: =IF(Y84<0,Y85,H84) | AB84: =K84 | AC84: =IF(AB84<0,AC85,AC85+AB84) | AD84: =$X$226-AC84 | AE84: =IF(AD84<0,AD85,K84)
H85: =ROUND(G85*D85,2) | K85: =ROUND(IF($I$28="YES",IF(G85>0,D85*(1-G85),0),0),2) | L85: =ROUND(IF(G85=0,D85,0),2) | M85: =ROUND(IF($I$28="NO",IF(G85>0,D85*(1-G85),0),0),2) | O85: =ROUND(IF(Z85<0,0,Z85),2) | P85: =ROUND(IF($I$28="YES",IF(AE85<0,0,AE85),0),2) | W85: =H85 | X85: =IF(W85<0,X86,X86+W85) | Y85: =$W$226-X85 | Z85: =IF(Y85<0,Y86,H85) | AB85: =K85 | AC85: =IF(AB85<0,AC86,AC86+AB85) | AD85: =$X$226-AC85 | AE85: =IF(AD85<0,AD86,K85)
H86: =ROUND(G86*D86,2) | K86: =ROUND(IF($I$28="YES",IF(G86>0,D86*(1-G86),0),0),2) | L86: =ROUND(IF(G86=0,D86,0),2) | M86: =ROUND(IF($I$28="NO",IF(G86>0,D86*(1-G86),0),0),2) | O86: =ROUND(IF(Z86<0,0,Z86),2) | P86: =ROUND(IF($I$28="YES",IF(AE86<0,0,AE86),0),2) | W86: =H86 | X86: =IF(W86<0,X87,X87+W86) | Y86: =$W$226-X86 | Z86: =IF(Y86<0,Y87,H86) | AB86: =K86 | AC86: =IF(AB86<0,AC87,AC87+AB86) | AD86: =$X$226-AC86 | AE86: =IF(AD86<0,AD87,K86)
H87: =ROUND(G87*D87,2) | K87: =ROUND(IF($I$28="YES",IF(G87>0,D87*(1-G87),0),0),2) | L87: =ROUND(IF(G87=0,D87,0),2) | M87: =ROUND(IF($I$28="NO",IF(G87>0,D87*(1-G87),0),0),2) | O87: =ROUND(IF(Z87<0,0,Z87),2) | P87: =ROUND(IF($I$28="YES",IF(AE87<0,0,AE87),0),2) | W87: =H87 | X87: =IF(W87<0,X88,X88+W87) | Y87: =$W$226-X87 | Z87: =IF(Y87<0,Y88,H87) | AB87: =K87 | AC87: =IF(AB87<0,AC88,AC88+AB87) | AD87: =$X$226-AC87 | AE87: =IF(AD87<0,AD88,K87)
H88: =ROUND(G88*D88,2) | K88: =ROUND(IF($I$28="YES",IF(G88>0,D88*(1-G88),0),0),2) | L88: =ROUND(IF(G88=0,D88,0),2) | M88: =ROUND(IF($I$28="NO",IF(G88>0,D88*(1-G88),0),0),2) | O88: =ROUND(IF(Z88<0,0,Z88),2) | P88: =ROUND(IF($I$28="YES",IF(AE88<0,0,AE88),0),2) | W88: =H88 | X88: =IF(W88<0,X89,X89+W88) | Y88: =$W$226-X88 | Z88: =IF(Y88<0,Y89,H88) | AB88: =K88 | AC88: =IF(AB88<0,AC89,AC89+AB88) | AD88: =$X$226-AC88 | AE88: =IF(AD88<0,AD89,K88)
H89: =ROUND(G89*D89,2) | K89: =ROUND(IF($I$28="YES",IF(G89>0,D89*(1-G89),0),0),2) | L89: =ROUND(IF(G89=0,D89,0),2) | M89: =ROUND(IF($I$28="NO",IF(G89>0,D89*(1-G89),0),0),2) | O89: =ROUND(IF(Z89<0,0,Z89),2) | P89: =ROUND(IF($I$28="YES",IF(AE89<0,0,AE89),0),2) | W89: =H89 | X89: =IF(W89<0,X90,X90+W89) | Y89: =$W$226-X89 | Z89: =IF(Y89<0,Y90,H89) | AB89: =K89 | AC89: =IF(AB89<0,AC90,AC90+AB89) | AD89: =$X$226-AC89 | AE89: =IF(AD89<0,AD90,K89)
H90: =ROUND(G90*D90,2) | K90: =ROUND(IF($I$28="YES",IF(G90>0,D90*(1-G90),0),0),2) | L90: =ROUND(IF(G90=0,D90,0),2) | M90: =ROUND(IF($I$28="NO",IF(G90>0,D90*(1-G90),0),0),2) | O90: =ROUND(IF(Z90<0,0,Z90),2) | P90: =ROUND(IF($I$28="YES",IF(AE90<0,0,AE90),0),2) | W90: =H90 | X90: =IF(W90<0,X91,X91+W90) | Y90: =$W$226-X90 | Z90: =IF(Y90<0,Y91,H90) | AB90: =K90 | AC90: =IF(AB90<0,AC91,AC91+AB90) | AD90: =$X$226-AC90 | AE90: =IF(AD90<0,AD91,K90)
H91: =ROUND(G91*D91,2) | K91: =ROUND(IF($I$28="YES",IF(G91>0,D91*(1-G91),0),0),2) | L91: =ROUND(IF(G91=0,D91,0),2) | M91: =ROUND(IF($I$28="NO",IF(G91>0,D91*(1-G91),0),0),2) | O91: =ROUND(IF(Z91<0,0,Z91),2) | P91: =ROUND(IF($I$28="YES",IF(AE91<0,0,AE91),0),2) | W91: =H91 | X91: =IF(W91<0,X92,X92+W91) | Y91: =$W$226-X91 | Z91: =IF(Y91<0,Y92,H91) | AB91: =K91 | AC91: =IF(AB91<0,AC92,AC92+AB91) | AD91: =$X$226-AC91 | AE91: =IF(AD91<0,AD92,K91)
H92: =ROUND(G92*D92,2) | K92: =ROUND(IF($I$28="YES",IF(G92>0,D92*(1-G92),0),0),2) | L92: =ROUND(IF(G92=0,D92,0),2) | M92: =ROUND(IF($I$28="NO",IF(G92>0,D92*(1-G92),0),0),2) | O92: =ROUND(IF(Z92<0,0,Z92),2) | P92: =ROUND(IF($I$28="YES",IF(AE92<0,0,AE92),0),2) | W92: =H92 | X92: =IF(W92<0,X93,X93+W92) | Y92: =$W$226-X92 | Z92: =IF(Y92<0,Y93,H92) | AB92: =K92 | AC92: =IF(AB92<0,AC93,AC93+AB92) | AD92: =$X$226-AC92 | AE92: =IF(AD92<0,AD93,K92)
H93: =ROUND(G93*D93,2) | K93: =ROUND(IF($I$28="YES",IF(G93>0,D93*(1-G93),0),0),2) | L93: =ROUND(IF(G93=0,D93,0),2) | M93: =ROUND(IF($I$28="NO",IF(G93>0,D93*(1-G93),0),0),2) | O93: =ROUND(IF(Z93<0,0,Z93),2) | P93: =ROUND(IF($I$28="YES",IF(AE93<0,0,AE93),0),2) | W93: =H93 | X93: =IF(W93<0,X94,X94+W93) | Y93: =$W$226-X93 | Z93: =IF(Y93<0,Y94,H93) | AB93: =K93 | AC93: =IF(AB93<0,AC94,AC94+AB93) | AD93: =$X$226-AC93 | AE93: =IF(AD93<0,AD94,K93)
... H219: =ROUND(G219*D219,2) | K219: =ROUND(IF($I$28="YES",IF(G219>0,D219*(1-G219),0),0),2) | L219: =ROUND(IF(G219=0,D219,0),2) | M219: =ROUND(IF($I$28="NO",IF(G219>0,D219*(1-G219),0),0),2) | O219: =ROUND(IF(Z219<0,0,Z219),2) | P219: =ROUND(IF($I$28="YES",IF(AE219<0,0,AE219),0),2) | W219: =H219 | X219: =IF(W219<0,X220,X220+W219) | Y219: =$W$226-X219 | Z219: =IF(Y219<0,Y220,H219) | AB219: =K219 | AC219: =IF(AB219<0,AC220,AC220+AB219) | AD219: =$X$226-AC219 | AE219: =IF(AD219<0,AD220,K219)
X220: 0 | Y220: 0 | AC220: 0 | AD220: 0
H222: Federal Share | K222: Toll Credits | L222: State Funds | N222: Time Extension | O222: Federal Share for Project Modification Letter | P222: Toll Credits for Project Modification Letter
H223: =SUM(H70:J219) | K223: =SUM(K70:K219) | L223: =SUM(L70:L219) | M223: =SUM(M70:M219) | N223: =SUM(N70:N219) | O223: =SUM(O70:O219) | P223: =SUM(P70:P219)
B225: Modification Total Amount: | E225: =SUM(D70:F219) | H225: Comparison of Modifications with Project Contingencies: | L225: Federal | O225: Toll Credits | Q225: State | W225: Federal | X225: Toll Credits | Y225: State
L226: =ROUND(W226,2) | O226: =ROUND(X226,2) | Q226: =ROUND(Y226,2) | W226: =IF((H223)<=(L60+SUM(L235:N384)),0,(H223)-(L60+SUM(L235:N384))) | X226: =IF((K223)<=(N60+SUM(O235:P384)),0,(K223)-(N60+SUM(O235:P384))) | Y226: =IF((L223+M223)<=(R60+P60+SUM(Q235:U384)),0,(L223+M223)-(R60+P60+SUM(Q235:U384)))
B227: Revised Contract Amount (all Funds): | E227: =E62+E225 | H227: Does Contract Modification Exceed Contingencies? | L227: =IF(L226>0,"YES. PRHTA needs to identify additional federal funds.","NO additional federal funds needed.") | O227: =IF(O226>0,"YES. PRHTA needs to identify additional toll credits.","NO additional toll credits needed.") | Q227: =IF(Q226>0,"YES. PRHTA needs to identify additional state funds.","NO additional state funds needed.") | W227: Federal Funds Needed:
B228: Amount of Federal Funds Needed (FMIS): | E228: =IF(W228>0,W228,0) | H228: NOTE: PRHTA FEDERAL LIAISON OFFICE AND BUDGET OFFICE WILL VERIFY THE VALUES IN THE CELLS OF FEDERAL, TOLL CREDITS AND STATE FUNDS TO IDENTIFY THE NEED FOR ADDITIONAL FUNDS IN THE PROJECT. | W228: =(H223+K223)-(L60+N60+SUM(L235:N384)+SUM(O235:P384))
B229: Amount of State Funds Needed (FMIS): | E229: =IF(Q226>0,Q226,0)
B231: AS INDICATED IN THE PROJECT MODIFICATION REQUEST LETTERS (THE LETTERS ARE DEVELOPED BY THE PRHTA FEDERAL LIAISON OFFICE AND EVALUATED/APPROVED BY THE FHWA PR/USVI DIVISION. FUNDS INFORMATION IN THE LETTERS WILL BE ACCESSED THROUGH A FOLDER IN A CLOUD PLATFORM):
B232: Obligations Amount (excludes Payroll, Mileage and Diets) | F232: Total Cost | J232: Federal Funds | L232: Federal Share | O232: Toll Credits | Q232: State Funds
B234: Original Project Funds | F234: =J234+Q234 | J234: =L234+O234 | L234: =K60 | O234: =M60 | Q234: =O61
B235: Modification #1 | F235: =J235+Q235 | J235: =L235+O235 | L235: 0 | O235: 0 | Q235: 448133
B236: Modification #2 | F236: =J236+Q236 | J236: =L236+O236
B237: Modification #3 | F237: =J237+Q237 | J237: =L237+O237
B238: Modification #4 | F238: =J238+Q238 | J238: =L238+O238
B239: Modification #5 | F239: =J239+Q239 | J239: =L239+O239
B240: Modification #6 | F240: =J240+Q240 | J240: =L240+O240
B241: Modification #7 | F241: =J241+Q241 | J241: =L241+O241
B242: Modification #8 | F242: =J242+Q242 | J242: =L242+O242
B243: Modification #9 | F243: =J243+Q243 | J243: =L243+O243
B244: Modification #10 | F244: =J244+Q244 | J244: =L244+O244
B245: Modification #11 | F245: =J245+Q245 | J245: =L245+O245
B246: Modification #12 | F246: =J246+Q246 | J246: =L246+O246
B247: Modification #13 | F247: =J247+Q247 | J247: =L247+O247
... B384: Modification #150 | F384: =J384+Q384 | J384: =L384+O384
B385: Revised Amount | F385: =SUM(F234:I384) | J385: =SUM(J234:K384) | L385: =SUM(L234:N384) | O385: =SUM(O234:P384) | Q385: =SUM(Q234:U384)

Sheet Data Analysis
A1: Report Date | B1: Project No. | C1: Federal No. | D1: Oracle No. | E1: Project Title | F1: Contractor | G1: Contract Beginning Date | H1: Original Contract Time | I1: Original Termination Date: | J1: Total Time Extensions (Days): | K1: Revised Termination Date: | L1: Change in Contract Time (%): | M1: % of Time Completed to Date: | N1: Change in Contract Amount (%): | O1: % Work Performed to Date: | P1: Estimated Completion Date: | Q1: Project End Date (FMIS): | R1: Eng. Contract Estimate: | S1: Total Construction Cost: | T1: Number of CHO documents: | U1: Number of EWO documents: | V1: Revised Contract Amount: | W1: Obligation Amount: | X1: Amount of Federal Funds Needed (FMIS): | Y1: Amount of State Funds Needed (FMIS):
A2: =IF('CML Report'!E14=0," ",'CML Report'!E14) | B2: =IF('CML Report'!E8=0," ",'CML Report'!E8) | C2: =IF('CML Report'!E9=0," ",'CML Report'!E9) | D2: =IF('CML Report'!E10=0," ",'CML Report'!E10) | E2: =IF('CML Report'!E11=0," ",'CML Report'!E11) | F2: =IF('CML Report'!E12=0," ",'CML Report'!E12) | G2: =IF('CML Report'!T8=0," ",'CML Report'!T8) | H2: =IF('CML Report'!T9=0," ",'CML Report'!T9) | I2: =IF('CML Report'!T10=0," ",'CML Report'!T10) | J2: =IF('CML Report'!T11=0," ",'CML Report'!T11) | K2: =IF('CML Report'!T12=0," ",'CML Report'!T12) | L2: =IF('CML Report'!T13=0,0,'CML Report'!T13) | M2: =IF('CML Report'!T14=0,0,'CML Report'!T14) | N2: =IF('CML Report'!T15=0,0,'CML Report'!T15) | O2: =IF('CML Report'!T16=0,0,'CML Report'!T16) | P2: =IF('CML Report'!T17=0," ",'CML Report'!T17) | Q2: =IF('CML Report'!T19=0," ",'CML Report'!T19) | R2: =IF('CML Report'!E62=0,0,'CML Report'!E62) | S2: =IF('CML Report'!E63=0,0,'CML Report'!E63) | T2: =IF('CML Report'!E17=0,0,'CML Report'!E17) | U2: =IF('CML Report'!E18=0,0,'CML Report'!E18) | V2: =IF('CML Report'!E227=0,0,'CML Report'!E227) | W2: =IF('CML Report'!F385=0,0,'CML Report'!F385) | X2: =IF('CML Report'!E228=0,0,'CML Report'!E228) | Y2: =IF('CML Report'!E229=0,0,'CML Report'!E229)
